canal/__init__.py
canal/server.py
canal_mqtt-0.0.1.dist-info/LICENSE
canal_mqtt-0.0.1.dist-info/METADATA
canal_mqtt-0.0.1.dist-info/WHEEL
canal_mqtt-0.0.1.dist-info/top_level.txt
canal_mqtt-0.0.1.dist-info/RECORD
