Metadata-Version: 2.1
Name: canal-mqtt
Version: 0.0.1
Summary: Transfer data through public MQTT brokers using TLS
Home-page: https://github.com/anderson-/canal
Maintainer: Anderson Antunes
Maintainer-email: anderson.utf@gmail.com
License: UNKNOWN
Platform: UNKNOWN
License-File: LICENSE
Requires-Dist: paho-mqtt
